moxel/__init__.py
moxel/_cli.py
moxel/_params.py
moxel/utils.py
pymoxel-0.5.0.post0.dist-info/licenses/LICENSE
pymoxel-0.5.0.post0.dist-info/METADATA
pymoxel-0.5.0.post0.dist-info/WHEEL
pymoxel-0.5.0.post0.dist-info/entry_points.txt
pymoxel-0.5.0.post0.dist-info/top_level.txt
pymoxel-0.5.0.post0.dist-info/RECORD
