Metadata-Version: 2.4
Name: pymoxel
Version: 0.5.0.post0
Summary: Package for parallel calculation of energy voxels.
Author-email: "Antonios P. Sarikas" <antonios.sarikas@gmail.com>
License-Expression: GPL-3.0-only
Project-URL: Homepage, https://github.com/adosar/moxel
Project-URL: Documentation, https://moxel.readthedocs.io
Project-URL: Changelog, https://moxel.readthedocs.io/en/stable/changes.html
Classifier: Programming Language :: Python :: 3
Classifier: Operating System :: POSIX :: Linux
Requires-Python: >=3.10
License-File: LICENSE
Requires-Dist: numpy>=1.26.4
Requires-Dist: jsonargparse[signatures]>=4.37.0
Requires-Dist: pymatgen
Requires-Dist: tqdm
Provides-Extra: docs
Requires-Dist: sphinx==7.3.7; extra == "docs"
Requires-Dist: sphinx-design; extra == "docs"
Requires-Dist: sphinx-copybutton; extra == "docs"
Requires-Dist: sphinx-rtd-theme; extra == "docs"
Requires-Dist: sphinx-issues; extra == "docs"
Dynamic: license-file
